README.md
setup.cfg
setup.py
distributions/Binomialdistribution.py
distributions/Gaussiandistribution.py
distributions/Generaldistribution.py
distributions/__init__.py
gabi_distributions.egg-info/PKG-INFO
gabi_distributions.egg-info/SOURCES.txt
gabi_distributions.egg-info/dependency_links.txt
gabi_distributions.egg-info/top_level.txt