Metadata-Version: 1.2
Name: gabi-distributions
Version: 0.0.1
Summary: Package for Gaussian and Bionomial Distributions
Home-page: UNKNOWN
Author: Ahmed Gamaleldin
Author-email: ahmedgamal1496@gmail.com
License: UNKNOWN
Platform: UNKNOWN
Classifier: Programming Language :: Python :: 3
Classifier: License :: OSI Approved :: MIT License
Classifier: Operating System :: OS Independent
Requires-Python: >=3.6
